ptwordpress/__init__.py
ptwordpress/_version.py
ptwordpress/ptwordpress.py
ptwordpress/modules/__init__.py
ptwordpress/modules/file_writer.py
ptwordpress/modules/guessing.py
ptwordpress/modules/helpers.py
ptwordpress/modules/release_badges.py
ptwordpress/modules/routes_walker.py
ptwordpress/modules/security_tools_identifier.py
ptwordpress/modules/source_discover.py
ptwordpress/modules/user_discover.py
ptwordpress/modules/version_by_sources.py
ptwordpress/modules/wpscan_api.py
ptwordpress/modules/api/__init__.py
ptwordpress/modules/api/comments.py
ptwordpress/modules/plugins/__init__.py
ptwordpress/modules/plugins/emails.py
ptwordpress/modules/plugins/hashes.py
ptwordpress/modules/plugins/media_downloader.py
ptwordpress/modules/plugins/yoast.py
ptwordpress/modules/wordlists/__init__.py
ptwordpress/modules/wordlists/admins.txt
ptwordpress/modules/wordlists/backups.txt
ptwordpress/modules/wordlists/configs.txt
ptwordpress/modules/wordlists/dangerous.txt
ptwordpress/modules/wordlists/directories.txt
ptwordpress/modules/wordlists/fpd.txt
ptwordpress/modules/wordlists/informations.txt
ptwordpress/modules/wordlists/logs.txt
ptwordpress/modules/wordlists/managements.txt
ptwordpress/modules/wordlists/passwords.txt
ptwordpress/modules/wordlists/plugin_list.csv
ptwordpress/modules/wordlists/plugins.txt
ptwordpress/modules/wordlists/readme.txt
ptwordpress/modules/wordlists/readme_small_plugins.txt
ptwordpress/modules/wordlists/readme_small_root.txt
ptwordpress/modules/wordlists/repositories.txt
ptwordpress/modules/wordlists/settings.txt
ptwordpress/modules/wordlists/sources2versions.csv
ptwordpress/modules/wordlists/statistics.txt
ptwordpress/modules/wordlists/unique_sources_for_version_identify.txt
ptwordpress/modules/wordlists/usernames.txt
ptwordpress/modules/wordpress_downloader/__init__.py
ptwordpress/modules/wordpress_downloader/plugins_downloader.py
ptwordpress/modules/wordpress_downloader/wordpres_downloader.py
ptwordpress-0.0.41.dist-info/licenses/LICENSE
ptwordpress-0.0.41.dist-info/METADATA
ptwordpress-0.0.41.dist-info/WHEEL
ptwordpress-0.0.41.dist-info/entry_points.txt
ptwordpress-0.0.41.dist-info/top_level.txt
ptwordpress-0.0.41.dist-info/RECORD
