Metadata-Version: 2.4
Name: ptwordpress
Version: 0.0.41
Summary: Wordpress Security Testing Tool
Home-page: https://www.penterep.com/
Author: Penterep
Author-email: info@penterep.com
License: GPLv3
Project-URL: homepage, https://www.penterep.com/
Project-URL: repository, https://github.com/penterep/ptwordpress
Project-URL: tracker, https://github.com/penterep/ptwordpress/issues
Classifier: Programming Language :: Python :: 3
Classifier: Programming Language :: Python :: Implementation :: CPython
Classifier: Environment :: Console
Classifier: Topic :: Security
Classifier: License :: OSI Approved :: GNU General Public License v3 (GPLv3)
Requires-Python: >=3.9
License-File: LICENSE
Requires-Dist: ptlibs<2,>=1.0.58
Requires-Dist: bs4
Requires-Dist: lxml
Requires-Dist: defusedxml
Requires-Dist: tqdm
Dynamic: author
Dynamic: author-email
Dynamic: classifier
Dynamic: description
Dynamic: description-content-type
Dynamic: home-page
Dynamic: license
Dynamic: license-file
Dynamic: project-url
Dynamic: requires-dist
Dynamic: requires-python
Dynamic: summary
